devctl_mcp/__init__.py
devctl_mcp/_version.py
devctl_mcp/process_manager.py
devctl_mcp/server.py
devctl_mcp-0.0.1.dist-info/METADATA
devctl_mcp-0.0.1.dist-info/WHEEL
devctl_mcp-0.0.1.dist-info/entry_points.txt
devctl_mcp-0.0.1.dist-info/top_level.txt
devctl_mcp-0.0.1.dist-info/RECORD
