Metadata-Version: 2.4
Name: devctl-mcp
Version: 0.0.1
Summary: A basic MCP (Model Context Protocol) server implementation
Author-email: Your Name <your.email@example.com>
License: MIT
Classifier: Development Status :: 3 - Alpha
Classifier: Intended Audience :: Developers
Classifier: License :: OSI Approved :: MIT License
Classifier: Programming Language :: Python :: 3
Classifier: Programming Language :: Python :: 3.8
Classifier: Programming Language :: Python :: 3.9
Classifier: Programming Language :: Python :: 3.10
Classifier: Programming Language :: Python :: 3.11
Classifier: Programming Language :: Python :: 3.12
Requires-Python: >=3.8
Requires-Dist: mcp>=1.0.0
Requires-Dist: importlib-metadata; python_version < "3.8"
Requires-Dist: pyyaml>=6.0
Provides-Extra: dev
Requires-Dist: uv; extra == "dev"
Requires-Dist: black; extra == "dev"
Requires-Dist: flake8; extra == "dev"
Requires-Dist: mypy; extra == "dev"
Requires-Dist: pytest; extra == "dev"
Requires-Dist: pytest-asyncio; extra == "dev"
Requires-Dist: setuptools-scm; extra == "dev"
